LAB-4/codes/xor_gate.vhdl
library ieee;
use ieee.std_logic_1164.all;

entity xor_gate is
    port (
        i1, i2 : in std_logic;
        o : out std_logic
    );
end entity xor_gate;

architecture behavioral of xor_gate is
begin
    o <= i1 xor i2;
end behavioral;

LAB-4/codes/bcd_to_gray_str.vhdl
library ieee;
use ieee.std_logic_1164.all;
use ieee.numeric_std.all;

entity bcd_to_gray is 
    port (
         BCD : in std_logic_vector(3 downto 0);
        Gray: out std_logic_vector(3 downto 0)
    );

end bcd_to_gray;

architecture structural of bcd_to_gray is 
component xor_gate
    port(i1, i2 : in std_logic;
        o: out std_logic);
end component;

begin
    label1: xor_gate port map(i1 => bcd(0), i2 => bcd(1), o => gray(0));
    label2: xor_gate port map(i1 => bcd(1), i2 => bcd(2), o => gray(1));
    label3: xor_gate port map(i1 => bcd(2), i2 => bcd(3), o => gray(2));
    label4: gray(3) <= bcd(3);

end structural;

LAB-4/codes/bcd_to_gray_tb.vhdl
library ieee;
use ieee.std_logic_1164.all;

entity bcd_to_gray_tb is

end bcd_to_gray_tb;

architecture bcd_to_gray_test of bcd_to_gray_tb is  
component bcd_to_gray is 
    port (
         BCD : in std_logic_vector(3 downto 0);
        Gray: out std_logic_vector(3 downto 0)
    );
end component;

    signal BCD_input , gray : std_logic_vector(3 downto 0);

    constant DELAY : time := 50 ps;
begin 
    UUT: bcd_to_gray port map(BCD => BCD_input, gray => Gray);

    Stimulus_process : process
    begin
        BCD_input <= "0000";
        wait for DELAY;
        BCD_input <= "0001";
        wait for DELAY;
        BCD_input <= "0010";
        wait for DELAY;
        BCD_input <= "0011";
        wait for DELAY;
        BCD_input <= "0100";
        wait for DELAY;
        BCD_input <= "0101";
        wait for DELAY;
        BCD_input <= "0110";
        wait for DELAY;
        BCD_input <= "0111";
        wait for DELAY;
        BCD_input <= "1000";
        wait for DELAY;
        BCD_input <= "1001";
        wait for DELAY;
        wait;
    end process;

end bcd_to_gray_test;

LAB-4/waves/bcd_to_gray.vcd
$date
  Fri Jan 26 21:59:01 2024
$end
$version
  GHDL v0
$end
$timescale
  1 fs
$end
$scope module standard $end
$upscope $end
$scope module std_logic_1164 $end
$upscope $end
$scope module numeric_std $end
$upscope $end
$scope module bcd_to_gray_tb $end
$var reg 4 ! bcd_input[3:0] $end
$var reg 4 " gray[3:0] $end
$scope module uut $end
$var reg 4 # bcd[3:0] $end
$var reg 4 $ gray[3:0] $end
$scope module label1 $end
$var reg 1 % i1 $end
$var reg 1 & i2 $end
$var reg 1 ' o $end
$upscope $end
$scope module label2 $end
$var reg 1 ( i1 $end
$var reg 1 ) i2 $end
$var reg 1 * o $end
$upscope $end
$scope module label3 $end
$var reg 1 + i1 $end
$var reg 1 , i2 $end
$var reg 1 - o $end
$upscope $end
$upscope $end
$upscope $end
$enddefinitions $end
#0
b0000 !
b0000 "
b0000 #
b0000 $
0%
0&
0'
0(
0)
0*
0+
0,
0-
#50000
b0001 !
b0001 "
b0001 #
b0001 $
1%
1'
#100000
b0010 !
b0011 "
b0010 #
b0011 $
0%
1&
1(
1*
#150000
b0011 !
b0010 "
b0011 #
b0010 $
1%
0'
#200000
b0100 !
b0110 "
b0100 #
b0110 $
0%
0&
0(
1)
1+
1-
#250000
b0101 !
b0111 "
b0101 #
b0111 $
1%
1'
#300000
b0110 !
b0101 "
b0110 #
b0101 $
0%
1&
1(
0*
#350000
b0111 !
b0100 "
b0111 #
b0100 $
1%
0'
#400000
b1000 !
b1100 "
b1000 #
b1100 $
0%
0&
0(
0)
0+
1,
#450000
b1001 !
b1101 "
b1001 #
b1101 $
1%
1'
