LAB-4/codes/or_gate.vhdl
library ieee;
use ieee.std_logic_1164.all;

entity or_gate is
    port(i1, i2 : in std_logic;
         o : out std_logic);
end entity or_gate;

architecture behavior of or_gate is
begin
    o <= i1 or i2;
end architecture behavior;

LAB-4/codes/and_gate.vhdl
library ieee;
use ieee.std_logic_1164.all;

entity and_gate is
    port(i1, i2 : in std_logic;
         o : out std_logic);
end entity and_gate;

architecture behavior of and_gate is
begin
    o <= i1 and i2;
end architecture behavior;

LAB-4/codes/not_gate.vhdl
library ieee;
use ieee.std_logic_1164.all;

entity not_gate is
    port(i : in std_logic;
         o : out std_logic);
end entity not_gate;

architecture behavior of not_gate is
begin
    o <= not i;
end architecture behavior;

LAB-4/codes/first_circuit_str.vhdl
library ieee;
use ieee.std_logic_1164.all;
use ieee.numeric_std.all;

entity first_circuit is 
    port(A, B, C, D : in std_logic;
        F : out std_logic);

end first_circuit;

architecture first_circuit_structural of first_circuit is 
    component and_gate 
        port(i1, i2 : in std_logic;
            o : out std_logic);

    end component;

    component or_gate 
        port(i1 , i2 : in std_logic;
            o :out std_logic);

    end component;

    component not_gate 
        port(i : in std_logic;
            o : out std_logic);

    end component;

    signal AB, Bcomp, BcompC, BCD, ABC : std_logic;

begin
    label1: and_gate port map(A, B, AB);
    label2: not_gate port map(B, Bcomp);
    label3: and_gate port map(Bcomp, C, BcompC);
    label4: and_gate port map(BcompC, D, BCD);
    label5: or_gate port map(AB, BcompC, ABC);
    label6: or_gate port map(BCD, ABC, F);

end first_circuit_structural;

LAB-4/codes/first_circuit_tb.vhdl
library ieee; 
use ieee.std_logic_1164.all;

entity first_circuit_tb is 
end first_circuit_tb;

architecture first_circuit_test of first_circuit_tb is 
    component first_circuit 
        port (
            A, B, C, D : in std_logic;
            F : out std_logic
        );
    end component;

    signal x1, x2, x3, x4 : std_logic;

begin 
    UUT : first_circuit port map (
        A => x1,
        B => x2,
        C => x3,
        D => x4,
        F => open 
    );
    
    Stimulus_process: process
begin
   x1 <= '0', '1' after 400 ps;
   x2 <= '0', '1' after 200 ps, '0' after 400 ps, '1' after 600 ps;
   x3 <= '0', '1' after 100 ps, '0' after 200 ps, '1' after 300 ps, '0' after 400 ps, '1' after 500 ps, '0' after 600 ps, '1' after 700 ps;
   x4 <= '0', '1' after 50 ps, '0' after 100 ps, '1' after 150 ps, '0' after 200 ps, '1' after 250 ps, '0' after 300 ps, '1' after 350 ps, '0' after 400 ps, '1' after 450 ps, '0' after 500 ps, '1' after 550 ps, '0' after 600 ps, '1' after 650 ps, '0' after 700 ps, '1' after 750 ps;
    wait;
    end process;

end first_circuit_test;

LAB-4/waves/first_circuit.vcd
$date
  Fri Jan 26 20:52:06 2024
$end
$version
  GHDL v0
$end
$timescale
  1 fs
$end
$scope module standard $end
$upscope $end
$scope module std_logic_1164 $end
$upscope $end
$scope module numeric_std $end
$upscope $end
$scope module first_circuit_tb $end
$var reg 1 ! x1 $end
$var reg 1 " x2 $end
$var reg 1 # x3 $end
$var reg 1 $ x4 $end
$scope module uut $end
$var reg 1 % a $end
$var reg 1 & b $end
$var reg 1 ' c $end
$var reg 1 ( d $end
$var reg 1 ) f $end
$var reg 1 * ab $end
$var reg 1 + bcomp $end
$var reg 1 , bcompc $end
$var reg 1 - bcd $end
$var reg 1 . abc $end
$scope module label1 $end
$var reg 1 / i1 $end
$var reg 1 0 i2 $end
$var reg 1 1 o $end
$upscope $end
$scope module label2 $end
$var reg 1 2 i $end
$var reg 1 3 o $end
$upscope $end
$scope module label3 $end
$var reg 1 4 i1 $end
$var reg 1 5 i2 $end
$var reg 1 6 o $end
$upscope $end
$scope module label4 $end
$var reg 1 7 i1 $end
$var reg 1 8 i2 $end
$var reg 1 9 o $end
$upscope $end
$scope module label5 $end
$var reg 1 : i1 $end
$var reg 1 ; i2 $end
$var reg 1 < o $end
$upscope $end
$scope module label6 $end
$var reg 1 = i1 $end
$var reg 1 > i2 $end
$var reg 1 ? o $end
$upscope $end
$upscope $end
$upscope $end
$enddefinitions $end
#0
0!
0"
0#
0$
0%
0&
0'
0(
0)
0*
1+
0,
0-
0.
0/
00
01
02
13
14
05
06
07
08
09
0:
0;
0<
0=
0>
0?
#50000
1$
1(
18
#100000
1#
0$
1'
0(
1)
1,
1.
15
16
17
08
1;
1<
1>
1?
#150000
1$
1(
1-
18
19
1=
#200000
1"
0#
0$
1&
0'
0(
0)
0+
0,
0-
0.
10
12
03
04
05
06
07
08
09
0;
0<
0=
0>
0?
#250000
1$
1(
18
#300000
1#
0$
1'
0(
15
08
#350000
1$
1(
18
#400000
1!
0"
0#
0$
1%
0&
0'
0(
1+
1/
00
02
13
14
05
08
#450000
1$
1(
18
#500000
1#
0$
1'
0(
1)
1,
1.
15
16
17
08
1;
1<
1>
1?
#550000
1$
1(
1-
18
19
1=
#600000
1"
0#
0$
1&
0'
0(
1*
0+
0,
0-
10
11
12
03
04
05
06
07
08
09
1:
0;
0=
#650000
1$
1(
18
#700000
1#
0$
1'
0(
15
08
#750000
1$
1(
18
