LAB-4/codes/three_or_gate.vhdl
library ieee;
use ieee.std_logic_1164.all;

entity three_or_gate is
    port(i1, i2, i3 : in std_logic;
         o : out std_logic);
end entity three_or_gate;

architecture behavior of three_or_gate is
begin
    o <= i1 or i2 or i3;
end  behavior;

LAB-4/codes/three_and_gate.vhdl
library ieee;
use ieee.std_logic_1164.all;

entity three_and_gate is
    port(i1, i2, i3 : in std_logic;
         o : out std_logic);
end entity three_and_gate;

architecture behavior of three_and_gate is
begin
    o <= i1 and i2 and i3;
end architecture behavior;

LAB-4/codes/not_gate.vhdl
library ieee;
use ieee.std_logic_1164.all;

entity not_gate is
    port(i : in std_logic;
         o : out std_logic);
end entity not_gate;

architecture behavior of not_gate is
begin
    o <= not i;
end architecture behavior;

LAB-4/codes/logic_function_str.vhdl
library ieee;
use ieee.std_logic_1164.all;
use ieee.numeric_std.all;

entity logic_function is 
    port(x1, x2, x3 : in std_logic;
        f : out std_logic);
end logic_function;

architecture structural of logic_function is 
    component three_and_gate 
        port(i1, i2, i3 : in std_logic;
            o : out std_logic);
    end component;

    component three_or_gate 
        port(i1, i2, i3 : in std_logic;
            o : out std_logic);
    end component;

    component not_gate 
        port(i : in std_logic;
            o : out std_logic);
    end component;

    signal x1c, x2c, x3c, xa, xb, xc : std_logic;  

begin
    label1 : not_gate port map (x1, x1c);
    label2 : not_gate port map (x2, x2c);
    label3 : not_gate port map (x3, x3c);
    label4 : three_and_gate port map (x1c, x2, x3, xa);
    label5 : three_and_gate port map (x1, x2c, x3, xb);
    label6 : three_and_gate port map (x1, x2, x3c, xc);
    label7 : three_or_gate port map (xa, xb, xc, f);
end structural;

LAB-4/codes/logic_function_tb.vhdl
library ieee;
use ieee.std_logic_1164.all;
use ieee.numeric_std.all;

entity logic_function_tb is 

end logic_function_tb;

architecture logic_function_test of logic_function_tb is
    component logic_function is 
        port(x1, x2, x3 : in std_logic;
            f : out std_logic);
    
    end component;
    signal a, b, c : std_logic;
begin
    UUT: logic_function port map (x1=>c, x2=>b, x3=>a);
     
    Stimulus_process : process
      begin
          a <= '0','1' after 400 ps;
          b <= '0','1' after 200 ps, '0' after 400 ps, '1' after 600 ps;
          c <= '0', '1' after 100 ps, '0' after 200 ps, '1' after 300 ps, '0' after 400 ps, '1' after 500 ps, '0' after 600 ps, '1' after 700 ps;

          wait for 800 ps;
wait;
    end process;

end logic_function_test;

LAB-4/waves/logic_function.vcd
$date
  Fri Jan 26 23:12:26 2024
$end
$version
  GHDL v0
$end
$timescale
  1 fs
$end
$scope module standard $end
$upscope $end
$scope module std_logic_1164 $end
$upscope $end
$scope module numeric_std $end
$upscope $end
$scope module logic_function_tb $end
$var reg 1 ! a $end
$var reg 1 " b $end
$var reg 1 # c $end
$scope module uut $end
$var reg 1 $ x1 $end
$var reg 1 % x2 $end
$var reg 1 & x3 $end
$var reg 1 ' f $end
$var reg 1 ( x1c $end
$var reg 1 ) x2c $end
$var reg 1 * x3c $end
$var reg 1 + xa $end
$var reg 1 , xb $end
$var reg 1 - xc $end
$scope module label1 $end
$var reg 1 . i $end
$var reg 1 / o $end
$upscope $end
$scope module label2 $end
$var reg 1 0 i $end
$var reg 1 1 o $end
$upscope $end
$scope module label3 $end
$var reg 1 2 i $end
$var reg 1 3 o $end
$upscope $end
$scope module label4 $end
$var reg 1 4 i1 $end
$var reg 1 5 i2 $end
$var reg 1 6 i3 $end
$var reg 1 7 o $end
$upscope $end
$scope module label5 $end
$var reg 1 8 i1 $end
$var reg 1 9 i2 $end
$var reg 1 : i3 $end
$var reg 1 ; o $end
$upscope $end
$scope module label6 $end
$var reg 1 < i1 $end
$var reg 1 = i2 $end
$var reg 1 > i3 $end
$var reg 1 ? o $end
$upscope $end
$scope module label7 $end
$var reg 1 @ i1 $end
$var reg 1 A i2 $end
$var reg 1 B i3 $end
$var reg 1 C o $end
$upscope $end
$upscope $end
$upscope $end
$enddefinitions $end
#0
0!
0"
0#
0$
0%
0&
0'
1(
1)
1*
0+
0,
0-
0.
1/
00
11
02
13
14
05
06
07
08
19
0:
0;
0<
0=
1>
0?
0@
0A
0B
0C
#100000
1#
1$
0(
1.
0/
04
18
1<
#200000
1"
0#
0$
1%
1(
0)
0.
1/
10
01
14
15
08
09
0<
1=
#300000
1#
1$
1'
0(
1-
1.
0/
04
18
1<
1?
1B
1C
#400000
1!
0"
0#
0$
0%
1&
0'
1(
1)
0*
0-
0.
1/
00
11
12
03
14
05
16
08
19
1:
0<
0=
0>
0?
0B
0C
#500000
1#
1$
1'
0(
1,
1.
0/
04
18
1;
1<
1A
1C
#600000
1"
0#
0$
1%
1'
1(
0)
1+
0,
0.
1/
10
01
14
15
17
08
09
0;
0<
1=
1@
0A
1C
#700000
1#
1$
0'
0(
0+
1.
0/
04
07
18
1<
0@
0C
